minumtium/__init__.py
minumtium/infra/__init__.py
minumtium/infra/authentication.py
minumtium/infra/database.py
minumtium/modules/__init__.py
minumtium/modules/idm.py
minumtium/modules/posts.py
minumtium-1.1.0.dist-info/LICENSE
minumtium-1.1.0.dist-info/METADATA
minumtium-1.1.0.dist-info/WHEEL
minumtium-1.1.0.dist-info/top_level.txt
minumtium-1.1.0.dist-info/RECORD
