Metadata-Version: 2.1
Name: minumtium
Version: 1.1.0
Summary: A very simple blogging library.
Home-page: https://github.com/danodic-dev/minumtium
Author: Danilo Guimaraes (danodic)
Author-email: danilo@danodic.dev
License: UNKNOWN
Project-URL: Bug Tracker, https://github.com/danodic-dev/minumtium/issues
Platform: UNKNOWN
Classifier: Development Status :: 3 - Alpha
Classifier: Programming Language :: Python :: 3
Classifier: License :: OSI Approved :: Apache Software License
Classifier: Operating System :: OS Independent
Requires-Python: >=3.6
License-File: LICENSE
Requires-Dist: pydantic
